{
	"archive" : {},
	"artifacts" : 
	[
		{
			"path" : "serialport/libserialport.a"
		}
	],
	"backtrace" : 1,
	"backtraceGraph" : 
	{
		"commands" : 
		[
			"add_library",
			"target_include_directories",
			"target_link_libraries"
		],
		"files" : 
		[
			"serialport/CMakeLists.txt"
		],
		"nodes" : 
		[
			{
				"file" : 0
			},
			{
				"command" : 0,
				"file" : 0,
				"line" : 3,
				"parent" : 0
			},
			{
				"command" : 1,
				"file" : 0,
				"line" : 5,
				"parent" : 0
			},
			{
				"command" : 2,
				"file" : 0,
				"line" : 7,
				"parent" : 0
			}
		]
	},
	"compileGroups" : 
	[
		{
			"compileCommandFragments" : 
			[
				{
					"fragment" : " "
				},
				{
					"fragment" : "-std=gnu++17"
				}
			],
			"includes" : 
			[
				{
					"backtrace" : 2,
					"path" : "/home/linyun/桌面/23-vision-ZhuRonghui/armo_detect/serialport/include"
				},
				{
					"backtrace" : 3,
					"isSystem" : true,
					"path" : "/usr/local/include/opencv4"
				}
			],
			"language" : "CXX",
			"sourceIndexes" : 
			[
				0
			]
		}
	],
	"id" : "serialport::@7b0139fbcd90484fcb96",
	"name" : "serialport",
	"nameOnDisk" : "libserialport.a",
	"paths" : 
	{
		"build" : "serialport",
		"source" : "serialport"
	},
	"sourceGroups" : 
	[
		{
			"name" : "Source Files",
			"sourceIndexes" : 
			[
				0
			]
		}
	],
	"sources" : 
	[
		{
			"backtrace" : 1,
			"compileGroupIndex" : 0,
			"path" : "serialport/src/SerialPort.cpp",
			"sourceGroupIndex" : 0
		}
	],
	"type" : "STATIC_LIBRARY"
}
